ctkentrymsg/__init__.py
ctkentrymsg/ctkentrymsg.py
ctkentrymsg-0.0.5.dist-info/LICENSE
ctkentrymsg-0.0.5.dist-info/METADATA
ctkentrymsg-0.0.5.dist-info/WHEEL
ctkentrymsg-0.0.5.dist-info/top_level.txt
ctkentrymsg-0.0.5.dist-info/RECORD
