Metadata-Version: 2.1
Name: ctkentrymsg
Version: 0.0.5
Summary: CTkEntry widget with message functionality
Home-page: https://github.com/shine-jayakumar/CTkEntryMsg
Author: Shine Jayakumar
Author-email: shinejayakumar@yahoo.com
License: MIT
Project-URL: Documentation, https://github.com/shine-jayakumar/CTkEntryMsg
Project-URL: Source, https://github.com/shine-jayakumar/CTkEntryMsg
Keywords: ctkentrymsg,customtkinter,tkinter,ctkentry, ctkentry-show-message
Platform: UNKNOWN
Classifier: Development Status :: 4 - Beta
Classifier: License :: OSI Approved :: MIT License
Classifier: Programming Language :: Python
Classifier: Programming Language :: Python :: 3.10
Classifier: Operating System :: OS Independent
Classifier: Topic :: Software Development
Classifier: Topic :: Software Development :: Libraries
Classifier: Topic :: Software Development :: Libraries :: Python Modules
Requires-Python: >=3.7
License-File: LICENSE
Requires-Dist: customtkinter
